pydantic_to_django_model/__init__.py
pydantic_to_django_model/py.typed
pydantic_to_django_model/pydantic_to_django_model.py
pydantic_to_django_model-0.1.0.dist-info/LICENSE
pydantic_to_django_model-0.1.0.dist-info/METADATA
pydantic_to_django_model-0.1.0.dist-info/WHEEL
pydantic_to_django_model-0.1.0.dist-info/RECORD
