Metadata-Version: 2.3
Name: pydantic-to-django-model
Version: 0.1.0
Summary: pydantic-to-django-model is a Python library that converts Pydantic BaseModels into Django ORM models.
License: MIT
Author: Ivan Ogasawara
Author-email: ivan.ogasawara@gmail.com
Requires-Python: >=3.10,<4
Classifier: License :: OSI Approved :: MIT License
Classifier: Programming Language :: Python :: 3
Classifier: Programming Language :: Python :: 3.10
Classifier: Programming Language :: Python :: 3.11
Classifier: Programming Language :: Python :: 3.12
Classifier: Programming Language :: Python :: 3.13
Requires-Dist: eval-type-backport (>=0.2.2,<0.3.0)
Requires-Dist: typeguard (>=4.0)
